{
  "name": "saasservicemgmt",
  "name_pretty": "SaaS Runtime API",
  "product_documentation": "https://cloud.google.com/saas-runtime/docs/overview",
  "client_documentation": "https://cloud.google.com/nodejs/docs/reference/saasservicemgmt/latest",
  "issue_tracker": "https://github.com/googleapis/google-cloud-node/issues",
  "release_level": "preview",
  "language": "nodejs",
  "repo": "googleapis/google-cloud-node",
  "distribution_name": "@google-cloud/saasservicemgmt",
  "api_id": "saasservicemgmt.googleapis.com",
  "default_version": "v1beta1",
  "requires_billing": true,
  "library_type": "GAPIC_AUTO",
  "api_shortname": "saasservicemgmt"
}

